adventure/__init__.py
cyoa_game/__init__.py
cyoa_game/adventure.py
cyoa_game/config.py
cyoa_game/main.py
game/__init__.py
game/config.py
game/main.py
choose_your_own_adventure-0.4.0.dist-info/METADATA
choose_your_own_adventure-0.4.0.dist-info/WHEEL
choose_your_own_adventure-0.4.0.dist-info/entry_points.txt
choose_your_own_adventure-0.4.0.dist-info/top_level.txt
choose_your_own_adventure-0.4.0.dist-info/RECORD
