Metadata-Version: 2.1
Name: choose-your-own-adventure
Version: 0.4.0
Summary: Choose Your Own Adventure (CYOA) stories using the Language Model LLM.
Home-page: https://github.com/GaelReinaudi/choose-your-own-adventure
Author: Gael Reinaudi
Author-email: gael.reinaudi@gmail.com
Classifier: Programming Language :: Python :: 3
Classifier: Operating System :: OS Independent
Requires-Python: >=3.10
